golog/__init__.py
golog/alerts.py
golog/decorators.py
golog/log.py
golog/tools.py
golog-0.4.7.dist-info/METADATA
golog-0.4.7.dist-info/WHEEL
golog-0.4.7.dist-info/top_level.txt
golog-0.4.7.dist-info/RECORD
