Metadata-Version: 2.1
Name: golog
Version: 0.4.7
Summary: The package contains some useful general functions for logging, and more.
Home-page: https://github.com/lollococce/golog
Author: Lorenzo Coacci
Author-email: lorenzo@coacci.it
License: MIT
Platform: UNKNOWN
Classifier: Programming Language :: Python :: 3
Classifier: License :: OSI Approved :: MIT License
Classifier: Natural Language :: English
Requires-Dist: termcolor
Requires-Dist: alive-progress
Requires-Dist: twilio
Requires-Dist: slackclient
Requires-Dist: validators
